odoo/addons/pos_prevent_double_closing/README.rst
odoo/addons/pos_prevent_double_closing/__init__.py
odoo/addons/pos_prevent_double_closing/__manifest__.py
odoo/addons/pos_prevent_double_closing/i18n/fr.po
odoo/addons/pos_prevent_double_closing/i18n/pos_prevent_double_closing.pot
odoo/addons/pos_prevent_double_closing/models/__init__.py
odoo/addons/pos_prevent_double_closing/models/pos_session.py
odoo/addons/pos_prevent_double_closing/readme/CONTRIBUTORS.rst
odoo/addons/pos_prevent_double_closing/readme/DESCRIPTION.rst
odoo/addons/pos_prevent_double_closing/static/description/duplicated_entries.png
odoo/addons/pos_prevent_double_closing/static/description/icon.png
odoo/addons/pos_prevent_double_closing/static/description/index.html
odoo/addons/pos_prevent_double_closing/tests/__init__.py
odoo/addons/pos_prevent_double_closing/tests/test_module.py
odoo12_addon_pos_prevent_double_closing-12.0.1.0.2.dist-info/METADATA
odoo12_addon_pos_prevent_double_closing-12.0.1.0.2.dist-info/WHEEL
odoo12_addon_pos_prevent_double_closing-12.0.1.0.2.dist-info/top_level.txt
odoo12_addon_pos_prevent_double_closing-12.0.1.0.2.dist-info/RECORD
